setup.py
distro_gauss_binomial/Binomialdistribution.py
distro_gauss_binomial/Gaussiandistribution.py
distro_gauss_binomial/Generaldistribution.py
distro_gauss_binomial/__init__.py
distro_gauss_binomial.egg-info/PKG-INFO
distro_gauss_binomial.egg-info/SOURCES.txt
distro_gauss_binomial.egg-info/dependency_links.txt
distro_gauss_binomial.egg-info/not-zip-safe
distro_gauss_binomial.egg-info/top_level.txt