Metadata-Version: 1.0
Name: distro-gauss-binomial
Version: 0.1
Summary: Gaussian and Binomial distributions
Home-page: UNKNOWN
Author: sagarika debchoudhury
Author-email: sagarikachoudhury14@gmail.com
License: UNKNOWN
Platform: UNKNOWN
